{"name":"Kast","tagline":"open source program similar to wirecast","body":"# kast\r\n\r\n#Description\r\n\r\nKCast is a Free Open Source [WireCast](http://www.telestream.net/wirecast/features.htm) clone\r\n\r\n# Features\r\n\r\n##Production\r\n* Live compositing with multiple layers\r\n* Live switching\r\n* Titles\r\n* Transitions (Fade, Cut)\r\n* Picture-In-Picture\r\n* Pan Tilt Zoom control\r\n\r\n## Distribution\r\n* Create playlists\r\n* h.264 x264 encoding\r\n* RTMP streaming\r\n\r\n##Inputs\r\n* Video\r\n  * Screen capture (Local, Remote,OpenGL)\r\n  * RTMP\r\n  * Web streams\r\n  * IP cameras \r\n  * Cameras: USB, FireWire\r\n  * SmartPhones\r\n\r\n* Audio\r\n  * Microphones: USB, XLR, Unbalanced\r\n  * Audio mixers\r\n\r\n# Preliminary Gstreamer Pipeline\r\n![Preliminary Gstreamer Pipeline](https://raw.githubusercontent.com/cpyarger/kast/master/Preliminary%20Gstreamer%20Pipeline.png)\r\n","google":"","note":"Don't delete this file! It's used internally to help with page regeneration."}